{
  "$schema": "./quiz_schema.json",
  "videoConfig": {
    "source": "video.mp4",
    "startOffset": 0,
    "endPadding": 5
  },
  "quizSchedule": [
    {
      "time": 10,
      "quizId": "1",
      "title": "Basic Concepts Quiz",
      "description": "Testing understanding of initial concepts"
    },
    {
      "time": 60,
      "quizId": "2",
      "title": "Core Principles Quiz",
      "description": "Evaluating comprehension of core principles"
    },
    {
      "time": 120,
      "quizId": "3",
      "title": "True/False Assessment",
      "description": "Quick true/false check on key points"
    },
    {
      "time": 180,
      "quizId": "4",
      "title": "Final Understanding Check",
      "description": "Final assessment of lecture comprehension"
    }
  ],
  "quizzes": {
    "1": {
      "title": "Basic Concepts Quiz",
      "description": "Testing understanding of initial concepts",
      "present_items": 1,
      "timeLimit": 120,
      "questions": [
        {
          "id": "1.1",
          "question": "What is the capital of France?",
          "type": "multipleChoice",
          "options": ["Berlin", "Paris", "London"],
          "correctAnswer": "b",
          "points": 5,
          "feedback": {
            "correct": "Correct! Paris is indeed the capital of France.",
            "incorrect": "Incorrect. The capital of France is Paris."
          }
        },
        {
          "id": "1.2",
          "question": "What is the chemical symbol for water?",
          "type": "multipleChoice",
          "options": ["H2O", "CO2", "NaCl"],
          "correctAnswer": "a",
          "points": 5,
          "feedback": {
            "correct": "Correct! H2O is the chemical symbol for water.",
            "incorrect": "Incorrect. Water's chemical symbol is H2O."
          }
        }
      ]
    },
    "2": {
      "title": "Core Principles Quiz",
      "description": "Evaluating comprehension of core principles",
      "present_items": "ALL",
      "timeLimit": 180,
      "questions": [
        {
          "id": "2.1",
          "question": "What is the largest planet in our solar system?",
          "type": "multipleChoice",
          "options": ["Earth", "Jupiter", "Saturn"],
          "correctAnswer": "b",
          "points": 5,
          "feedback": {
            "correct": "Correct! Jupiter is the largest planet.",
            "incorrect": "Incorrect. Jupiter is the largest planet in our solar system."
          }
        },
        {
          "id": "2.2",
          "question": "What is the speed of light in vacuum?",
          "type": "multipleChoice",
          "options": ["300,000 km/s", "150,000 km/s", "500,000 km/s"],
          "correctAnswer": "a",
          "points": 5,
          "feedback": {
            "correct": "Correct! Light travels at 300,000 km/s in vacuum.",
            "incorrect": "Incorrect. The speed of light in vacuum is 300,000 km/s."
          }
        }
      ]
    },
    "3": {
      "title": "True/False Assessment",
      "description": "Quick true/false check on key points",
      "present_items": 1,
      "timeLimit": 60,
      "questions": [
        {
          "id": "3.1",
          "question": "The Earth is flat.",
          "type": "trueFalse",
          "correctAnswer": false,
          "points": 5,
          "feedback": {
            "correct": "Correct! The Earth is spherical.",
            "incorrect": "Incorrect. The Earth is not flat."
          }
        },
        {
          "id": "3.2",
          "question": "Water boils at 100 degrees Celsius at sea level.",
          "type": "trueFalse",
          "correctAnswer": true,
          "points": 5,
          "feedback": {
            "correct": "Correct! Water boils at 100°C at sea level.",
            "incorrect": "Incorrect. Water does boil at 100°C at sea level."
          }
        }
      ]
    },
    "4": {
      "title": "Final Understanding Check",
      "description": "Final assessment of lecture comprehension",
      "present_items": "ALL",
      "timeLimit": 300,
      "questions": [
        {
          "id": "4.1",
          "question": "What is the name of the university you are studying at?",
          "type": "shortAnswer",
          "points": 5,
          "validation": {
            "required": true,
            "minLength": 2,
            "maxLength": 100
          }
        },
        {
          "id": "4.2",
          "question": "What is the name of this module?",
          "type": "shortAnswer",
          "points": 5,
          "validation": {
            "required": true,
            "minLength": 2,
            "maxLength": 100
          }
        }
      ]
    }
  }
}
